happyrobot/__init__.py
happyrobot/models/__init__.py
happyrobot/models/call.py
happyrobot/models/event.py
happyrobot/models/message.py
happyrobot/src/__init__.py
happyrobot/src/utils/__init__.py
happyrobot/src/utils/date_utils.py
happyrobot/src/utils/message_utils.py
happyrobot-0.2.9.dist-info/LICENSE
happyrobot-0.2.9.dist-info/METADATA
happyrobot-0.2.9.dist-info/WHEEL
happyrobot-0.2.9.dist-info/top_level.txt
happyrobot-0.2.9.dist-info/RECORD
